[ {
  "Team Name" : "Buffalo Sabres",
  "Epoch Time of Scrap" : "1749558171361",
  "Year" : "1990",
  "Win %" : "0.388"
}, {
  "Team Name" : "Hartford Whalers",
  "Epoch Time of Scrap" : "1749558171493",
  "Year" : "1990",
  "Win %" : "0.388"
}, {
  "Team Name" : "Minnesota North Stars",
  "Epoch Time of Scrap" : "1749558171563",
  "Year" : "1990",
  "Win %" : "0.338"
}, {
  "Team Name" : "New York Islanders",
  "Epoch Time of Scrap" : "1749558171675",
  "Year" : "1990",
  "Win %" : "0.312"
}, {
  "Team Name" : "Quebec Nordiques",
  "Epoch Time of Scrap" : "1749558171802",
  "Year" : "1990",
  "Win %" : "0.2"
}, {
  "Team Name" : "Toronto Maple Leafs",
  "Epoch Time of Scrap" : "1749558171882",
  "Year" : "1990",
  "Win %" : "0.287"
}, {
  "Team Name" : "Vancouver Canucks",
  "Epoch Time of Scrap" : "1749558171952",
  "Year" : "1990",
  "Win %" : "0.35"
}, {
  "Team Name" : "Winnipeg Jets",
  "Epoch Time of Scrap" : "1749558172051",
  "Year" : "1990",
  "Win %" : "0.325"
}, {
  "Team Name" : "Buffalo Sabres",
  "Epoch Time of Scrap" : "1749558172139",
  "Year" : "1991",
  "Win %" : "0.388"
}, {
  "Team Name" : "Calgary Flames",
  "Epoch Time of Scrap" : "1749558172197",
  "Year" : "1991",
  "Win %" : "0.388"
}, {
  "Team Name" : "Hartford Whalers",
  "Epoch Time of Scrap" : "1749558173316",
  "Year" : "1991",
  "Win %" : "0.325"
}, {
  "Team Name" : "Quebec Nordiques",
  "Epoch Time of Scrap" : "1749558173493",
  "Year" : "1991",
  "Win %" : "0.25"
}, {
  "Team Name" : "San Jose Sharks",
  "Epoch Time of Scrap" : "1749558173566",
  "Year" : "1991",
  "Win %" : "0.212"
}, {
  "Team Name" : "Toronto Maple Leafs",
  "Epoch Time of Scrap" : "1749558173613",
  "Year" : "1991",
  "Win %" : "0.375"
}, {
  "Team Name" : "Edmonton Oilers",
  "Epoch Time of Scrap" : "1749558173786",
  "Year" : "1992",
  "Win %" : "0.31"
}, {
  "Team Name" : "Hartford Whalers",
  "Epoch Time of Scrap" : "1749558173861",
  "Year" : "1992",
  "Win %" : "0.31"
}, {
  "Team Name" : "Ottawa Senators",
  "Epoch Time of Scrap" : "1749558174995",
  "Year" : "1992",
  "Win %" : "0.119"
}, {
  "Team Name" : "San Jose Sharks",
  "Epoch Time of Scrap" : "1749558175108",
  "Year" : "1992",
  "Win %" : "0.131"
}, {
  "Team Name" : "Tampa Bay Lightning",
  "Epoch Time of Scrap" : "1749558175186",
  "Year" : "1992",
  "Win %" : "0.274"
}, {
  "Team Name" : "Mighty Ducks of Anaheim",
  "Epoch Time of Scrap" : "1749558175317",
  "Year" : "1993",
  "Win %" : "0.393"
}, {
  "Team Name" : "Edmonton Oilers",
  "Epoch Time of Scrap" : "1749558175452",
  "Year" : "1993",
  "Win %" : "0.298"
}, {
  "Team Name" : "Florida Panthers",
  "Epoch Time of Scrap" : "1749558176532",
  "Year" : "1993",
  "Win %" : "0.393"
}, {
  "Team Name" : "Hartford Whalers",
  "Epoch Time of Scrap" : "1749558176616",
  "Year" : "1993",
  "Win %" : "0.321"
}, {
  "Team Name" : "Los Angeles Kings",
  "Epoch Time of Scrap" : "1749558176704",
  "Year" : "1993",
  "Win %" : "0.321"
}, {
  "Team Name" : "Ottawa Senators",
  "Epoch Time of Scrap" : "1749558176816",
  "Year" : "1993",
  "Win %" : "0.167"
}, {
  "Team Name" : "San Jose Sharks",
  "Epoch Time of Scrap" : "1749558176877",
  "Year" : "1993",
  "Win %" : "0.393"
}, {
  "Team Name" : "Tampa Bay Lightning",
  "Epoch Time of Scrap" : "1749558176943",
  "Year" : "1993",
  "Win %" : "0.357"
}, {
  "Team Name" : "Winnipeg Jets",
  "Epoch Time of Scrap" : "1749558177026",
  "Year" : "1993",
  "Win %" : "0.286"
}, {
  "Team Name" : "Mighty Ducks of Anaheim",
  "Epoch Time of Scrap" : "1749558177085",
  "Year" : "1994",
  "Win %" : "0.333"
}, {
  "Team Name" : "Dallas Stars",
  "Epoch Time of Scrap" : "1749558177198",
  "Year" : "1994",
  "Win %" : "0.354"
} ]